Metadata-Version: 2.1
Name: mysqlx-generator
Version: 1.5.3
Summary: mysqlx-generator is a model code generator from db tables for MySqlx.
Home-page: https://gitee.com/summry/mysqlx/blob/master/generator.md
Author: summry
Author-email: xiazhongbiao@126.com
License: UNKNOWN
Keywords: MySQL,mysqlx,python
Platform: UNKNOWN
Requires-Python: >=3.5
